web_to_struct
